ffcv_pl/__init__.py
ffcv_pl/datasets/__init__.py
ffcv_pl/datasets/image.py
ffcv_pl/datasets/image_label.py
ffcv_pl/ffcv_utils/__init__.py
ffcv_pl/ffcv_utils/custom_augmentations.py
ffcv_pl/ffcv_utils/generate_dataset.py
ffcv_pl-0.1.3.dist-info/METADATA
ffcv_pl-0.1.3.dist-info/WHEEL
ffcv_pl-0.1.3.dist-info/top_level.txt
ffcv_pl-0.1.3.dist-info/RECORD
