Metadata-Version: 2.1
Name: ffcv-pl
Version: 0.1.3
Summary: manage fast data loading with ffcv and pytorch lightning
Home-page: https://github.com/SerezD/ffcv_pytorch_lightning
Author: DSerez
License: MIT
